screenpy_pyotp/__init__.py
screenpy_pyotp/__version__.py
screenpy_pyotp/py.typed
screenpy_pyotp/abilities/__init__.py
screenpy_pyotp/abilities/authenticate_with_2fa.py
screenpy_pyotp-4.0.1.dist-info/LICENSE
screenpy_pyotp-4.0.1.dist-info/METADATA
screenpy_pyotp-4.0.1.dist-info/WHEEL
screenpy_pyotp-4.0.1.dist-info/top_level.txt
screenpy_pyotp-4.0.1.dist-info/RECORD
