Metadata-Version: 2.1
Name: screenpy-pyotp
Version: 4.0.1
Summary: ScreenPy extension to enable interacting with PyOTP.
Home-page: https://github.com/ScreenPyHQ/screenpy_pyotp
Author: Perry Goy
Author-email: perry.goy@gmail.com
License: UNKNOWN
Platform: UNKNOWN
Classifier: Operating System :: OS Independent
Classifier: Programming Language :: Python :: 3 :: Only
Classifier: Development Status :: 5 - Production/Stable
Classifier: Intended Audience :: Developers
Classifier: Topic :: Software Development :: Quality Assurance
Classifier: Topic :: Software Development :: Testing
Classifier: Topic :: Software Development :: Testing :: BDD
Classifier: Natural Language :: English
Classifier: License :: OSI Approved :: MIT License
License-File: LICENSE
Requires-Dist: screenpy (>=4.0.0)
Requires-Dist: pyotp (<2.7,>=2.6.0)
